[{"id":"38ffd657.49c7f2","type":"ui_template","z":"c1515bc3.c46638","group":"b0494336.bf02b8","name":"Background","order":0,"width":0,"height":0,"format":"<style>\n    body {\n        background-image: url(\"/tech.png\");\n        background-size: cover;\n        background-position: center; \n    }\n</style>","storeOutMessages":true,"fwdInMessages":true,"templateScope":"global","x":170,"y":120,"wires":[["289a4a4c.9cb6ae"]]},{"id":"3dbaa4fd.6c04e4","type":"mqtt in","z":"c1515bc3.c46638","name":"","topic":"sheepstorm/sensori","qos":"0","broker":"bfb27da6.659978","x":150,"y":380,"wires":[["4f659a80.e93d14"]]},{"id":"4f659a80.e93d14","type":"json","z":"c1515bc3.c46638","name":"json","property":"payload","action":"","pretty":false,"x":310,"y":380,"wires":[["9903c214.dae738","6041c7ec.e007f8","b34f8a1a.814078"]]},{"id":"9903c214.dae738","type":"function","z":"c1515bc3.c46638","name":"Leggi sensore 1","func":"msg.payload = msg.payload.s1;\nreturn msg;","outputs":1,"noerr":0,"x":520,"y":280,"wires":[["9e41a7a.674d258","74a61074.e76938"]]},{"id":"9e41a7a.674d258","type":"ui_chart","z":"c1515bc3.c46638","name":"","group":"2d4543c1.3d73ec","order":1,"width":"5","height":"5","label":"History","chartType":"line","legend":"false","xformat":"HH:mm","interpolate":"linear","nodata":"","dot":false,"ymin":"","ymax":"","removeOlder":"12","removeOlderPoints":"","removeOlderUnit":"3600","cutout":0,"useOneColor":false,"colors":["#1f77b4","#aec7e8","#ff7f0e","#2ca02c","#98df8a","#d62728","#ff9896","#9467bd","#c5b0d5"],"useOldStyle":false,"x":740,"y":240,"wires":[[],[]]},{"id":"74a61074.e76938","type":"ui_gauge","z":"c1515bc3.c46638","name":"","group":"2d4543c1.3d73ec","order":2,"width":"0","height":"0","gtype":"gage","title":"Live","label":"°C","format":"{{value}}","min":0,"max":"100","colors":["#00b500","#e6e600","#ca3838"],"seg1":"","seg2":"","x":730,"y":300,"wires":[]},{"id":"289a4a4c.9cb6ae","type":"debug","z":"c1515bc3.c46638","name":"","active":true,"tosidebar":true,"console":false,"tostatus":false,"complete":"payload","x":330,"y":120,"wires":[]},{"id":"ae3c7b6.79dba88","type":"ui_template","z":"c1515bc3.c46638","group":"94f76c83.9c283","name":"","order":0,"width":"6","height":"4","format":"<a href=\"https://www.google.com\">\n<center><img src=\"/sheep.png\" alt=\"Logo Sheep\" height=\"90\" width=\"150\"></center>\n</a>","storeOutMessages":true,"fwdInMessages":true,"templateScope":"local","x":160,"y":180,"wires":[[]]},{"id":"c59d104b.ba059","type":"ui_template","z":"c1515bc3.c46638","group":"2d4543c1.3d73ec","name":"","order":0,"width":"6","height":"4","format":"<a href=\"https://www.google.com\">\n<center><img src=\"/temp.jpg\" alt=\"Logo Temp\" height=\"130\" width=\"130\"></center>\n</a>","storeOutMessages":true,"fwdInMessages":true,"templateScope":"local","x":880,"y":280,"wires":[[]]},{"id":"6041c7ec.e007f8","type":"function","z":"c1515bc3.c46638","name":"Leggi sensore 2","func":"msg.payload = msg.payload.s2;\nreturn msg;","outputs":1,"noerr":0,"x":520,"y":400,"wires":[["71fdcf56.5c281","18715add.ff833d"]]},{"id":"71fdcf56.5c281","type":"ui_chart","z":"c1515bc3.c46638","name":"","group":"c844f3b4.46088","order":1,"width":"5","height":"5","label":"History","chartType":"line","legend":"false","xformat":"HH:mm","interpolate":"linear","nodata":"","dot":false,"ymin":"","ymax":"","removeOlder":"12","removeOlderPoints":"","removeOlderUnit":"3600","cutout":0,"useOneColor":false,"colors":["#1f77b4","#aec7e8","#ff7f0e","#2ca02c","#98df8a","#d62728","#ff9896","#9467bd","#c5b0d5"],"useOldStyle":false,"x":740,"y":360,"wires":[[],[]]},{"id":"18715add.ff833d","type":"ui_gauge","z":"c1515bc3.c46638","name":"","group":"c844f3b4.46088","order":2,"width":"0","height":"0","gtype":"gage","title":"Live","label":"°C","format":"{{value}}","min":0,"max":"100","colors":["#00b500","#e6e600","#ca3838"],"seg1":"","seg2":"","x":730,"y":420,"wires":[]},{"id":"19b19ccc.7de27b","type":"ui_template","z":"c1515bc3.c46638","group":"c844f3b4.46088","name":"","order":0,"width":"6","height":"4","format":"<a href=\"https://www.google.com\">\n<center><img src=\"/light.png\" alt=\"Logo Temp\" height=\"130\" width=\"130\"></center>\n</a>","storeOutMessages":true,"fwdInMessages":true,"templateScope":"local","x":880,"y":400,"wires":[[]]},{"id":"b34f8a1a.814078","type":"function","z":"c1515bc3.c46638","name":"Leggi sensore 3","func":"msg.payload = msg.payload.s3;\nreturn msg;","outputs":1,"noerr":0,"x":520,"y":520,"wires":[["116bb509.b51173","71ab5de8.a462f4"]]},{"id":"116bb509.b51173","type":"ui_chart","z":"c1515bc3.c46638","name":"","group":"72add1b3.67667","order":1,"width":"5","height":"5","label":"History","chartType":"line","legend":"false","xformat":"HH:mm","interpolate":"linear","nodata":"","dot":false,"ymin":"","ymax":"","removeOlder":"12","removeOlderPoints":"","removeOlderUnit":"3600","cutout":0,"useOneColor":false,"colors":["#1f77b4","#aec7e8","#ff7f0e","#2ca02c","#98df8a","#d62728","#ff9896","#9467bd","#c5b0d5"],"useOldStyle":false,"x":740,"y":480,"wires":[[],[]]},{"id":"71ab5de8.a462f4","type":"ui_gauge","z":"c1515bc3.c46638","name":"","group":"72add1b3.67667","order":2,"width":"0","height":"0","gtype":"gage","title":"Live","label":"°C","format":"{{value}}","min":0,"max":"100","colors":["#00b500","#e6e600","#ca3838"],"seg1":"","seg2":"","x":730,"y":540,"wires":[]},{"id":"dd92eecf.737ee","type":"ui_template","z":"c1515bc3.c46638","group":"72add1b3.67667","name":"","order":0,"width":"6","height":"4","format":"<a href=\"https://www.google.com\">\n<center><img src=\"/umidita.png\" alt=\"Logo Temp\" height=\"130\" width=\"130\"></center>\n</a>","storeOutMessages":true,"fwdInMessages":true,"templateScope":"local","x":880,"y":520,"wires":[[]]},{"id":"80b1aa14.3c0d7","type":"ui_slider","z":"c1515bc3.c46638","name":"","label":"Slider 2","group":"b1920540.8e8c28","order":2,"width":0,"height":0,"passthru":true,"topic":"slider2","min":0,"max":"100","step":1,"x":200,"y":660,"wires":[["fb744b0a.946b78"]]},{"id":"3dd1d41f.2f5a1c","type":"ui_switch","z":"c1515bc3.c46638","name":"","label":"Switch 1","group":"b1920540.8e8c28","order":4,"width":0,"height":0,"passthru":true,"decouple":"false","topic":"switch1","style":"","onvalue":"true","onvalueType":"bool","onicon":"","oncolor":"","offvalue":"false","offvalueType":"bool","officon":"","offcolor":"","x":200,"y":780,"wires":[["fb744b0a.946b78"]]},{"id":"b7ec4b66.c9ac88","type":"ui_template","z":"c1515bc3.c46638","group":"b1920540.8e8c28","name":"","order":10,"width":"6","height":"4","format":"<a href=\"https://www.google.com\">\n<center><img src=\"/temp.jpg\" alt=\"Logo Temp\" height=\"130\" width=\"130\"></center>\n</a>","storeOutMessages":true,"fwdInMessages":true,"templateScope":"local","x":60,"y":820,"wires":[[]]},{"id":"6b7f8df6.eeeadc","type":"ui_slider","z":"c1515bc3.c46638","name":"","label":"Slider 1","group":"b1920540.8e8c28","order":1,"width":0,"height":0,"passthru":true,"topic":"slider1","min":0,"max":"100","step":1,"x":200,"y":620,"wires":[["fb744b0a.946b78"]]},{"id":"e80192e4.90aec8","type":"ui_slider","z":"c1515bc3.c46638","name":"","label":"Slider 3","group":"b1920540.8e8c28","order":3,"width":0,"height":0,"passthru":true,"topic":"slider3","min":0,"max":"100","step":1,"x":200,"y":700,"wires":[["fb744b0a.946b78"]]},{"id":"80a7067d.fb5e6","type":"ui_switch","z":"c1515bc3.c46638","name":"","label":"Switch 2","group":"b1920540.8e8c28","order":5,"width":0,"height":0,"passthru":true,"decouple":"false","topic":"switch2","style":"","onvalue":"true","onvalueType":"bool","onicon":"","oncolor":"","offvalue":"false","offvalueType":"bool","officon":"","offcolor":"","x":200,"y":820,"wires":[["fb744b0a.946b78"]]},{"id":"25d9f670.08046a","type":"ui_switch","z":"c1515bc3.c46638","name":"","label":"Switch 3","group":"b1920540.8e8c28","order":6,"width":0,"height":0,"passthru":true,"decouple":"false","topic":"switch3","style":"","onvalue":"true","onvalueType":"bool","onicon":"","oncolor":"","offvalue":"false","offvalueType":"bool","officon":"","offcolor":"","x":200,"y":860,"wires":[["fb744b0a.946b78"]]},{"id":"64be54e3.60bcc4","type":"ui_button","z":"c1515bc3.c46638","name":"","group":"b1920540.8e8c28","order":7,"width":0,"height":0,"passthru":false,"label":"Comando 1","color":"","bgcolor":"","icon":"","payload":"true","payloadType":"bool","topic":"puls1","x":210,"y":940,"wires":[["fb744b0a.946b78"]]},{"id":"883d04a4.5b172","type":"ui_button","z":"c1515bc3.c46638","name":"","group":"b1920540.8e8c28","order":8,"width":0,"height":0,"passthru":false,"label":"Comando 2","color":"","bgcolor":"","icon":"","payload":"true","payloadType":"bool","topic":"puls2","x":210,"y":980,"wires":[["fb744b0a.946b78"]]},{"id":"b2ee52eb.05d358","type":"ui_button","z":"c1515bc3.c46638","name":"","group":"b1920540.8e8c28","order":9,"width":0,"height":0,"passthru":false,"label":"Comando 3","color":"","bgcolor":"","icon":"","payload":"true","payloadType":"bool","topic":"puls3","x":210,"y":1020,"wires":[["fb744b0a.946b78"]]},{"id":"796eda5b.f2aed4","type":"ui_template","z":"c1515bc3.c46638","group":"94f76c83.9c283","name":"","order":0,"width":"6","height":"5","format":"<a href=\"https://www.google.com\">\n<center><img src=\"/logo.png\" alt=\"Logo Gara\" height=\"160\" width=\"150\"></center>\n</a>","storeOutMessages":true,"fwdInMessages":true,"templateScope":"local","x":160,"y":220,"wires":[[]]},{"id":"49663517.bfc76c","type":"mqtt out","z":"c1515bc3.c46638","name":"","topic":"sheepstorm/attuatori","qos":"","retain":"","broker":"bfb27da6.659978","x":640,"y":820,"wires":[]},{"id":"fb744b0a.946b78","type":"template","z":"c1515bc3.c46638","name":"Wrapper","field":"payload","fieldType":"msg","format":"handlebars","syntax":"mustache","template":"{{topic}}:{{payload}}:","output":"str","x":460,"y":820,"wires":[["49663517.bfc76c"]]},{"id":"1bd5447e.26f544","type":"ui_template","z":"c1515bc3.c46638","group":"94f76c83.9c283","name":"","order":0,"width":"6","height":"4","format":"<a href=\"https://www.google.com\">\n<center><img src=\"/logouni.png\" alt=\"Logo Uni\" height=\"120\" width=\"150\"></center>\n</a>","storeOutMessages":true,"fwdInMessages":true,"templateScope":"local","x":160,"y":260,"wires":[[]]},{"id":"b0494336.bf02b8","type":"ui_group","z":"","name":"Jacopo","tab":"","disp":true,"width":"6","collapse":false},{"id":"bfb27da6.659978","type":"mqtt-broker","z":"","name":"","broker":"iot.eclipse.org","port":"1883","clientid":"","usetls":false,"compatmode":true,"keepalive":"60","cleansession":true,"willTopic":"","willQos":"0","willPayload":"","birthTopic":"","birthQos":"0","birthPayload":""},{"id":"2d4543c1.3d73ec","type":"ui_group","z":"","name":"Temperatura","tab":"47a99c44.8c07c4","order":2,"disp":true,"width":"6","collapse":false},{"id":"94f76c83.9c283","type":"ui_group","z":"","name":"Colonna start","tab":"47a99c44.8c07c4","order":1,"disp":true,"width":"6","collapse":false},{"id":"c844f3b4.46088","type":"ui_group","z":"","name":"Umidità","tab":"47a99c44.8c07c4","order":3,"disp":true,"width":"6","collapse":false},{"id":"72add1b3.67667","type":"ui_group","z":"","name":"Luce","tab":"47a99c44.8c07c4","order":4,"disp":true,"width":"6","collapse":false},{"id":"b1920540.8e8c28","type":"ui_group","z":"","name":"Attuatori","tab":"47a99c44.8c07c4","order":5,"disp":true,"width":"6","collapse":false},{"id":"47a99c44.8c07c4","type":"ui_tab","z":"","name":"Sheepstorm Desktop","icon":"dashboard","order":1}]
